{
    "basic_info": {
      "description_header": "Hi",
      "description": "👋 I'm Yurii Hlukhyi , aspiring software developer passionate about efficient, customer-oriented solutions with non-traditional background in infrastructure telecommunication, I’m studying JS right now, and planing to study Python in next couple of months. Let me tell you a little bit about myself: my greatest strength is perseverance, everything in my life, I achieved by working hard and smart, I’m always trying to find best solution. And if I’m failing, I like to take a step back to think around, and try again, until I succeed . I have consistently shown commitment and motivation in every company I worked. I meet set deadlines and objectives on time even if a have to work late. At the same time I don’t know when to stop, even tho I need a little break. Once I get to know people, I’m pretty good in teamwork, I believe that my skills and my ability to work in a team are valuable. In regards to the areas in which I could improve, I will be the first to admit that I struggled when interacting with people I don’t know well, I am still uncertain as to how to improve myself. But I think recognition of the problem is halfway to solve it.",
      "section_name": {
        "about": "About me",
        "projects": "Projects",
        "skills": "Skills",
        "experience": "Experience"
      }
    },
    "projects": [
      {
        "title": "Slot machine",
        "startDate": "2022",
        "description": "It's interactive slot machine page. That provides assistance for gambling addiction",
        "images": [
          "images/portfolio/animal-shelter/p1.jpg",
          "images/portfolio/animal-shelter/p2.jpg"
        ],
        "url": "https://team-vi.github.io/FVI/index.html",
        "technologies": [
          {
            "class": "devicon-html5-plain",
            "name": "HTML5"
          },
          {
            "class": "devicon-css3-plain",
            "name": "CSS"
          },
          {
            "class": "devicon-javascript-plain",
            "name": "JavaScript"
          }
        ]
      },
      {
        "title": "Gallery of Horns",
        "startDate": "2023",
        "description": "Fun little page, to practice React",
        "images": [
          "images/portfolio/photography/p1.jpg",
          "images/portfolio/photography/p2.jpg"
        ],
        "url": "https://dashing-dango-917830.netlify.app/",
        "technologies": [
          {
            "class": "devicon-html5-plain",
            "name": "HTML5"
          },
          {
            "class": "devicon-css3-plain",
            "name": "CSS"
          },
          {
            "class": "devicon-javascript-plain",
            "name": "JavaScript"
          }
        ]
      },
      {
        "title": "Salmon Cookie",
        "startDate": "2022",
        "description": "One of the first pages I was working on my 201. With ability to add adittional data, using local storage.",
        "images": [
          "images/portfolio/adventure/p1.jpg",
          "images/portfolio/adventure/p2.jpg"
        ],
        "url": "https://yhluk.github.io/cookie-stand/",
        "technologies": [
          {
            "class": "devicon-html5-plain",
            "name": "HTML5"
          },
          {
            "class": "devicon-css3-plain",
            "name": "CSS"
          },
          {
            "class": "devicon-javascript-plain",
            "name": "JavaScript"
          }
        ]
      }
    ],
    "experience": [
      {
        "company": "Code Fellows",
        "title": "Student",
        "years": "10.2022 - present",
        "mainTech": [
          
        ],
        "technologies": [
          "HTML5",
          "JavaScript",
          "Bootstrap",
          "React",
          ".NODE JS"
        ]
      },
      {
        "company": "Comcast Telecom",
        "title": "Cable Tech",
        "years": "06.2020 - present",
        "mainTech": [
         
        ],
        "technologies": [

        ]
      }
    ]
  }
